gitlab_utils/__init__.py
gitlab_utils/client.py
gitlab_utils/apis/__init__.py
gitlab_utils/apis/users.py
gitlab_utils-0.1.1.dist-info/METADATA
gitlab_utils-0.1.1.dist-info/WHEEL
gitlab_utils-0.1.1.dist-info/licenses/LICENSE
gitlab_utils-0.1.1.dist-info/RECORD
