Metadata-Version: 2.4
Name: gitlab-utils
Version: 0.1.1
Summary: A Python SDK for interacting with code.swecha.org using GitLab API v4.
Project-URL: Homepage, https://code.swecha.org/ranjithraj/gitlab-wrapper/
Project-URL: Issue Tracker, https://code.swecha.org/ranjithraj/gitlab-wrapper/issues
License: GNU General Public License v3.0
License-File: LICENSE
Requires-Python: >=3.11
Requires-Dist: httpx>=0.26.0
Requires-Dist: requests>=2.31.0
Provides-Extra: dev
Requires-Dist: pre-commit; extra == 'dev'
Requires-Dist: pytest; extra == 'dev'
Requires-Dist: python-dotenv; extra == 'dev'
Requires-Dist: requests-mock; extra == 'dev'
Requires-Dist: respx; extra == 'dev'
Requires-Dist: ruff; extra == 'dev'
